tool.py
google/__init__.py
google/attack.py
sphinxcontrib/__init__.py
sphinxcontrib/attack.py
wthtest/__init__.py
wthtest/testmodule1.py
wthtest-0.1.1.4.dist-info/METADATA
wthtest-0.1.1.4.dist-info/WHEEL
wthtest-0.1.1.4.dist-info/top_level.txt
wthtest-0.1.1.4.dist-info/RECORD
