Metadata-Version: 2.1
Name: wthtest
Version: 0.1.1.4
Summary: This is a test lib
Home-page: UNKNOWN
Author: wth
Author-email: UNKNOWN
License: UNKNOWN
Platform: UNKNOWN
